<?xml version="1.0"?>
<!--
  ~ eGov suite of products aim to improve the internal efficiency,transparency,
  ~    accountability and the service delivery of the government  organizations.
  ~
  ~     Copyright (C) <2015>  eGovernments Foundation
  ~
  ~     The updated version of eGov suite of products as by eGovernments Foundation
  ~     is available at http://www.egovernments.org
  ~
  ~     This program is free software: you can redistribute it and/or modify
  ~     it under the terms of the GNU General Public License as published by
  ~     the Free Software Foundation, either version 3 of the License, or
  ~     any later version.
  ~
  ~     This program is distributed in the hope that it will be useful,
  ~     but WITHOUT ANY WARRANTY; without even the implied warranty of
  ~     MERCHANTABILITY or FITNESS FOR A PARTICULAR PURPOSE.  See the
  ~     GNU General Public License for more details.
  ~
  ~     You should have received a copy of the GNU General Public License
  ~     along with this program. If not, see http://www.gnu.org/licenses/ or
  ~     http://www.gnu.org/licenses/gpl.html .
  ~
  ~     In addition to the terms of the GPL license to be adhered to in using this
  ~     program, the following additional terms are to be complied with:
  ~
  ~         1) All versions of this program, verbatim or modified must carry this
  ~            Legal Notice.
  ~
  ~         2) Any misrepresentation of the origin of the material is prohibited. It
  ~            is required that all modified versions of this material be marked in
  ~            reasonable ways as different from the original version.
  ~
  ~         3) This license does not grant any rights to any user of the program
  ~            with regards to rights under trademark law for use of the trade names
  ~            or trademarks of eGovernments Foundation.
  ~
  ~   In case of any queries, you can reach eGovernments Foundation at contact@egovernments.org.
  -->
<!DOCTYPE hibernate-mapping PUBLIC "-//Hibernate/Hibernate Mapping DTD 3.0//EN"
	"http://www.hibernate.org/dtd/hibernate-mapping-3.0.dtd">

<hibernate-mapping>
	<class name="org.egov.ptis.domain.entity.property.PropertyDetail"
		table="EGPT_PROPERTY_DETAIL">
		<id name="propertyDetailsID" column="ID" type="integer">
			<generator class="org.hibernate.id.enhanced.SequenceStyleGenerator">
				<param name="sequence_name">SEQ_EGPT_PROPERTY_DETAIL</param>
			</generator>
		</id>

		<discriminator column="PROPERTY_TYPE" />
		<timestamp name="updatedTime" column="UPDT_TIMESTAMP"
			access="property" unsaved-value="null" />

		<property name="propertyType" column="PROPERTY_TYPE"
			not-null="true" insert="false" update="false" />

		<many-to-one name="property" fetch="join"
			class="org.egov.ptis.domain.entity.property.PropertyImpl" column="id_property"
			unique="true" cascade="none" />

		<many-to-one name="propertyTypeMaster"
			class="org.egov.ptis.domain.entity.property.PropertyTypeMaster"
			column="ID_PROPERTYTYPEMASTER" unique="true" />

		<component name="sitalArea" class="org.egov.commons.Area">
			<property name="area" column="SITAL_AREA" />
			<property name="length" column="PROPERTY_LENGTH" />
			<property name="breadth" column="PROPERTY_BREADTH" />
		</component>

		<property name="fieldIrregular" column="IS_IRREGULAR" />

		<property name="noofFloors" column="NUM_FLOORS" type="integer" />

		<property name="dateOfCompletion" type="java.util.Date">
			<column name="DATEOFCOMPLETION" length="10" />
		</property>

		<many-to-one name="PropertyUsage"
			class="org.egov.ptis.domain.entity.property.PropertyUsage" column="ID_USG_MSTR" />

		<many-to-one name="propertyMutationMaster"
			class="org.egov.ptis.domain.entity.property.PropertyMutationMaster"
			column="ID_MUTATION" unique="true" />

		<property name="water_Meter_Num" column="WATER_METER_NUM" />

		<property name="elec_Meter_Num" column="ELEC_METER_NUM" />

		<property name="surveyNumber" column="SURVEY_NUM" />

		<property name="fieldVerified" column="IS_FIELD_VERIFIED"
			insert="false" />

		<property name="fieldVerificationDate" column="FIELD_VERIF_DATE"
			update="false" />

		<property name="cornerPlot" column="IS_CORNERPLOT" />
		<property name="comZone" column="IS_COMZONE" />

		<property name="manualAlv" column="MANUAL_ALV" />
		<property name="occupierName" column="OCCUPIER_NAME" />
		<property name="lift" column="lift" type="boolean" />
		<property name="toilets" column="toilets" type="boolean" />
		<property name="waterTap" column="watertap" type="boolean" />
		<property name="structure" column="structure" type="boolean" />
		<property name="electricity" column="electricity" type="boolean" />
		<property name="attachedBathRoom" column="attachedBathRoom"	type="boolean" />
		<property name="waterHarvesting" column="waterHarvesting" type="boolean" />
		<property name="cable" column="cable" type="boolean" />
		<property name="extentSite" column="extentsite" type="double" />
		<property name="extentAppartenauntLand" column="extent_appurtenant_land" type="double" />
		<property name="siteOwner" column="siteowner" type="java.lang.String" />
		<property name="currentCapitalValue" column="current_capitalValue"	type="double" />
		<property name="marketValue" column="marketvalue" type="double" />
		<property name="pattaNumber" column="pattanumber" type="java.lang.String" />
		<property name="categoryType" column="category_type" type="java.lang.String" />
		<property name="occupancyCertificationNo" column="occupancy_certificationno" type="java.lang.String" />
		<!-- <property name="appurtenantLandChecked" column="appurtenantland_checked" type="java.lang.Boolean"/> -->
		<property name="corrAddressDiff" column="corrAddressDiff" type="java.lang.Boolean"/>
		<many-to-one name="floorType" class="org.egov.ptis.domain.entity.property.FloorType" column="floorType" />
		<many-to-one name="roofType" class="org.egov.ptis.domain.entity.property.RoofType" column="roofType" />
		<many-to-one name="wallType" class="org.egov.ptis.domain.entity.property.WallType" column="wallType" />
		<many-to-one name="woodType" class="org.egov.ptis.domain.entity.property.WoodType" column="woodType" />
		<many-to-one name="apartment" class="org.egov.ptis.domain.entity.property.Apartment" column="apartment"/>
		<many-to-one name="propertyDepartment" class="org.egov.ptis.domain.entity.property.PropertyDepartment" column="pt_department"/>
		<many-to-one name="vacantLandPlotArea" class="org.egov.ptis.domain.entity.property.vacantland.VacantLandPlotArea" column="vlt_plot_area"/>
		<many-to-one name="layoutApprovalAuthority" class="org.egov.ptis.domain.entity.property.vacantland.LayoutApprovalAuthority" column="layout_approval_authority"/>
		<property name="layoutPermitNo" column="layout_permit_number" type="java.lang.String"/>
		<property name="layoutPermitDate" column="layout_permit_date" type="java.util.Date"/>

		<!-- <set name="floorDetails" order-by="FLOOR_NO" cascade="all" table="EGPT_FLOOR_DETAIL"> 
			<key column="ID_PROPERTY_DETAIL" not-null="true" /> <one-to-many class="org.egov.ptis.domain.entity.property.Floor" 
			/> </set> -->
		<bag name="floorDetails" cascade="all-delete-orphan" table="EGPT_FLOOR_DETAIL"
			inverse="true" order-by="id">
			<key>
				<column name="ID_PROPERTY_DETAIL" precision="22" scale="0"
					not-null="true" />
			</key>
			<one-to-many class="org.egov.ptis.domain.entity.property.Floor" />
		</bag>


		<many-to-one name="propertyOccupation"
			class="org.egov.ptis.domain.entity.property.PropertyOccupation"
			column="ID_OCCPN_MSTR" unique="true" />

		<component name="commBuiltUpArea" class="org.egov.commons.Area">
			<property name="area" column="COMMN_BUILTUP_AREA" />
		</component>

		<component name="plinthArea" class="org.egov.commons.Area">
			<property name="area" column="PLINTH_AREA" />
		</component>
		<component name="commVacantLand" class="org.egov.commons.Area">
			<property name="area" column="COMMN_VCNT_LAND" />
		</component>
		<component name="nonResPlotArea" class="org.egov.commons.Area">
			<property name="area" column="NONRES_PLOTAREA" />
		</component>

		<subclass name="org.egov.ptis.domain.entity.property.VacantProperty"
			discriminator-value="VacantProperty">
			<component name="totalBuiltupArea" class="org.egov.commons.Area">
				<property name="area" column="TOTAL_BUILTUP_AREA" />
			</component>
		</subclass>

		<subclass name="org.egov.ptis.domain.entity.property.BuiltUpProperty"
			discriminator-value="BuiltUpProperty">
			<component name="totalBuiltupArea" class="org.egov.commons.Area">
				<property name="area" column="TOTAL_BUILTUP_AREA" />
			</component>
		</subclass>
	</class>
</hibernate-mapping>
