<?xml version="1.0"?>
<!DOCTYPE hibernate-mapping PUBLIC "-//Hibernate/Hibernate Mapping DTD 3.0//EN"
"http://www.hibernate.org/dtd/hibernate-mapping-3.0.dtd">
<hibernate-mapping>
    <class name="org.egov.commons.Bankreconciliation" table="BANKRECONCILIATION">
        <id name="id" type="integer">
	    	<column name="ID" precision="22" scale="0" />
	    	<generator class="sequence">
	    		<param name="sequence_name">seq_bankreconciliation</param>
	    	</generator>
        </id>
         <many-to-one name="bankaccount" class="org.egov.commons.Bankaccount" fetch="select">
            <column name="BANKACCOUNTID" precision="22" scale="0" />
        </many-to-one>
        <property name="amount" type="big_decimal">
            <column name="AMOUNT" precision="15" />
        </property>
        <property name="transactiontype" type="string">
            <column name="TRANSACTIONTYPE" length="2" not-null="true" />
        </property>
        <property name="instrumentHeaderId" type="long">
            <column name="INSTRUMENTHEADERID" precision="22" scale="0" />
        </property>
    </class>
</hibernate-mapping>
