<?xml version="1.0"?>
<!DOCTYPE hibernate-mapping PUBLIC "-//Hibernate/Hibernate Mapping DTD 3.0//EN"
"http://www.hibernate.org/dtd/hibernate-mapping-3.0.dtd">
	<!-- Generated 10 Sep, 2009 12:59:28 PM by Hibernate Tools 3.2.0.CR1 -->
<hibernate-mapping auto-import="false">
	<class name="org.egov.erpcollection.models.Challan" table="EGCL_CHALLANHEADER">
		<id name="id" type="long">
			<column name="ID" precision="22" scale="0" />
			<generator class="sequence">
				<param name="sequence">SEQ_EGCL_CHALLANHEADER</param>
			</generator>
		</id>

		<many-to-one name="receiptHeader" class="org.egov.erpcollection.models.ReceiptHeader" fetch="select">
            <column name="RECEIPTID" precision="22" scale="0" />
        </many-to-one>
        
        <property name="challanNumber" type="string">
			<column name="CHALLANNUMBER" length="25" not-null="true" />
		</property>
		
		<property name="reasonForCancellation" type="string">
			<column name="REASONFORCANCELLATION" length="256" />
		</property>
		
		<property name="validUpto" column="VALIDUPTO" type="timestamp" />
		
		<property name="challanDate" column="CHALLANDATE" type="java.util.Date" not-null="true"/>
		
		<many-to-one name="status" class="org.egov.commons.EgwStatus" fetch="select">
			<column name="STATUSID" precision="22" scale="0" not-null="true" />
		</many-to-one>
		
		<many-to-one name="state" class="org.egov.infstr.models.State" cascade="all">
			<column name="WFSTATEID" />
		</many-to-one>
		
		<many-to-one name="service" class="org.egov.infstr.models.ServiceDetails"
			fetch="select">
			<column name="SERVICE_ID" precision="22" scale="0" />
		</many-to-one>
		
		<many-to-one name="voucherHeader" class="org.egov.commons.CVoucherHeader" fetch="select">
			<column name="VOUCHERHEADERID" />
		</many-to-one>
		
		<many-to-one name="createdBy" class="org.egov.lib.rjbac.user.UserImpl"
			fetch="select">
			<column name="CREATED_BY" precision="22" scale="0" />
		</many-to-one>
		
		<many-to-one name="modifiedBy" class="org.egov.lib.rjbac.user.UserImpl"
			fetch="select">
			<column name="MODIFIED_BY" precision="22" scale="0" />
		</many-to-one>
		
		<property name="createdDate" column="CREATED_DATE" type="timestamp" />
		<property name="modifiedDate" column="MODIFIED_DATE" type="timestamp" />
		
	</class>
	    
</hibernate-mapping>
