<?xml version="1.0"?>
<!DOCTYPE hibernate-mapping PUBLIC "-//Hibernate/Hibernate Mapping DTD 3.0//EN"
"http://www.hibernate.org/dtd/hibernate-mapping-3.0.dtd">
<!-- Generated Jul 9, 2007 3:21:11 PM by Hibernate Tools 3.2.0.b9 -->
<hibernate-mapping>
    <class name="org.egov.pims.model.Regularisation" table="EGEIS_REGULARISATION" >
        
        <id
	name="regularisationId"
	column="REGULARISATION_ID"
	type="int">
	<generator class="sequence">
		<param name="sequence">EGPIMS_REGULARISATION_SEQ</param>
	</generator>
	</id>
        <many-to-one name="postMstr" column="ID_POST" 
	class="org.egov.pims.commons.DesignationMaster" 
	/>
        <property name="regularisationDate" type="date">
            <column name="REGULARISATION_DATE" length="7" />
        </property>
        <property name="orderNo" type="string">
            <column name="ORDER_NO" length="256" />
        </property>
        <property name="orderDate" type="date">
            <column name="ORDER_DATE" length="7" />
        </property>
        
    </class>
</hibernate-mapping>
